pymeta/__init__.py
pymeta/__main__.py
pymetasec-1.1.1.dist-info/LICENSE
pymetasec-1.1.1.dist-info/METADATA
pymetasec-1.1.1.dist-info/WHEEL
pymetasec-1.1.1.dist-info/entry_points.txt
pymetasec-1.1.1.dist-info/top_level.txt
pymetasec-1.1.1.dist-info/RECORD
