Metadata-Version: 2.1
Name: pymetasec
Version: 1.1.1
Summary: Web scraper to download and extract file metadata
Home-page: https://github.com/m8sec/pymeta
Author: m8sec
License: GPLv3
Platform: Unix
Classifier: Environment :: Console
Classifier: Programming Language :: Python :: 3
Classifier: License :: OSI Approved :: GNU General Public License v3 or later (GPLv3+)
Classifier: Operating System :: Unix
Classifier: Topic :: Security
License-File: LICENSE
Requires-Dist: bs4
Requires-Dist: requests
